jaimead7_pyutils-0.2.0.dist-info/licenses/LICENSE
pyUtils/__init__.py
pyUtils/src/__init__.py
pyUtils/src/config.py
pyUtils/src/logs.py
pyUtils/src/no_instantiable.py
pyUtils/src/timing.py
pyUtils/src/validation.py
pyUtils/src/filesystem/__init__.py
pyUtils/src/filesystem/dirs.py
pyUtils/src/filesystem/files.py
pyUtils/test/__init__.py
pyUtils/test/test_config.py
pyUtils/test/test_logs.py
pyUtils/test/test_noInstantiable.py
pyUtils/test/test_timing.py
pyUtils/test/test_validation.py
pyUtils/test/test_filesystem/__init__.py
pyUtils/test/test_filesystem/test_dirs.py
pyUtils/test/test_filesystem/test_files.py
jaimead7_pyutils-0.2.0.dist-info/METADATA
jaimead7_pyutils-0.2.0.dist-info/WHEEL
jaimead7_pyutils-0.2.0.dist-info/top_level.txt
jaimead7_pyutils-0.2.0.dist-info/RECORD
