Metadata-Version: 2.4
Name: jaimead7-pyutils
Version: 0.2.0
Summary: Different utilities for general purpose usage on python projects.
Author-email: Jaimead7 <alvarez.diaz.jaime1@gmail.com>
Maintainer-email: Jaimead7 <alvarez.diaz.jaime1@gmail.com>
License-Expression: MIT
Project-URL: Homepage, https://github.com/Jaimead7/PyUtils
Project-URL: Repository, https://github.com/Jaimead7/PyUtils
Keywords: utilities,tools
Classifier: Programming Language :: Python :: 3.10
Classifier: Programming Language :: Python :: 3.11
Classifier: Programming Language :: Python :: 3.12
Classifier: Programming Language :: Python :: 3.13
Requires-Python: >=3.10
License-File: LICENSE
Requires-Dist: tomli>=2.2.1
Requires-Dist: tomli-w>=1.2.0
Requires-Dist: pyyaml>=6.0.2
Requires-Dist: typing_extensions>=4.14.1
Provides-Extra: dev
Requires-Dist: pytest>=8.3.4; extra == "dev"
Requires-Dist: wheel>=0.45.1; extra == "dev"
Requires-Dist: twine>=6.1.0; extra == "dev"
Requires-Dist: build>=1.3.0; extra == "dev"
Dynamic: license-file
